{
  "Jugador": {
    "Datito": {
      "Tipo": 6,
      "Nombre": "Machop",
      "Debilidades": [
        "Volador",
        "Psiquico",
        "Hada"
      ],
      "Resistencias": [
        "Roca",
        "Siniestro",
        "Bicho"
      ],
      "Movimientos": [
        {
          "Nombre": "Tackle",
          "TipoAtaque": 6,
          "Poder": 4
        },
        {
          "Nombre": "Golpe Karate",
          "TipoAtaque": 6,
          "Poder": 4
        },
        {
          "Nombre": "Pu\u00F1o Fuego",
          "TipoAtaque": 6,
          "Poder": 5
        }
      ]
    },
    "Caracteristicas": {
      "Salud": 30.92,
      "Ataque": 4,
      "Defensa": 8,
      "Velocidad": 10,
      "Nivel": 1
    }
  },
  "Rivales": [
    {
      "Datito": {
        "Tipo": 16,
        "Nombre": "Magnemite",
        "Debilidades": [
          "Fuego",
          "Lucha",
          "Tierra"
        ],
        "Resistencias": [
          "Acero",
          "Normal",
          "Volador",
          "Dragon",
          "Roca",
          "Planta",
          "Hada",
          "Hielo",
          "Psiquico",
          "Bicho",
          "Veneno"
        ],
        "Movimientos": [
          {
            "Nombre": "Golpe Acero",
            "TipoAtaque": 16,
            "Poder": 5
          },
          {
            "Nombre": "Lanzamiento",
            "TipoAtaque": 16,
            "Poder": 3
          },
          {
            "Nombre": "Cuchilla Giratoria",
            "TipoAtaque": 16,
            "Poder": 3
          }
        ]
      },
      "Caracteristicas": {
        "Salud": 100,
        "Ataque": 7,
        "Defensa": 2,
        "Velocidad": 10,
        "Nivel": 5
      }
    }
  ],
  "RivalActual": {
    "Datito": {
      "Tipo": 1,
      "Nombre": "Charmander",
      "Debilidades": [
        "Agua",
        "Tierra",
        "Roca"
      ],
      "Resistencias": [
        "Fuego",
        "Bicho",
        "Acero",
        "Hielo",
        "Planta",
        "Hada"
      ],
      "Movimientos": [
        {
          "Nombre": "Ascuas",
          "TipoAtaque": 1,
          "Poder": 1
        },
        {
          "Nombre": "Lanzallamas",
          "TipoAtaque": 1,
          "Poder": 3
        },
        {
          "Nombre": "Pirotecnia",
          "TipoAtaque": 1,
          "Poder": 2
        }
      ]
    },
    "Caracteristicas": {
      "Salud": 100,
      "Ataque": 8,
      "Defensa": 8,
      "Velocidad": 8,
      "Nivel": 10
    }
  }
}
